mazette.py
mazette-0.2.1.dist-info/METADATA
mazette-0.2.1.dist-info/WHEEL
mazette-0.2.1.dist-info/entry_points.txt
mazette-0.2.1.dist-info/licenses/LICENSE-APACHE
mazette-0.2.1.dist-info/licenses/LICENSE-MIT
mazette-0.2.1.dist-info/RECORD
