Metadata-Version: 2.4
Name: mazette
Version: 0.2.1
Summary: GitHub asset management with lock files and extensive configuration
Project-URL: Repository, https://github.com/freedomofpress/mazette
Author-email: Freedom of the Press Foundation <info@freedom.press>
License-File: LICENSE-APACHE
License-File: LICENSE-MIT
Keywords: assets,github,packaging
Requires-Python: >=3.9
Requires-Dist: colorama>=0.4.6
Requires-Dist: platformdirs>=4.3.8
Requires-Dist: requests>=2.32.3
Requires-Dist: semver>=3.0.4
Requires-Dist: toml>=0.10.2
